{"nodes": [{"id": "inventree_contrib_container_gunicorn_conf_py", "label": "gunicorn.conf.py", "file_type": "code", "source_file": "inventree/contrib/container/gunicorn.conf.py", "source_location": "L1"}, {"id": "gunicorn_conf_post_fork", "label": "post_fork()", "file_type": "code", "source_file": "inventree/contrib/container/gunicorn.conf.py", "source_location": "L45"}, {"id": "gunicorn_conf_rationale_1", "label": "Gunicorn configuration for InvenTree.", "file_type": "rationale", "source_file": "inventree/contrib/container/gunicorn.conf.py", "source_location": "L1"}, {"id": "gunicorn_conf_rationale_46", "label": "Post-fork hook to set up logging for each worker.", "file_type": "rationale", "source_file": "inventree/contrib/container/gunicorn.conf.py", "source_location": "L46"}], "edges": [{"source": "inventree_contrib_container_gunicorn_conf_py", "target": "logging", "relation": "imports", "confidence": "EXTRACTED", "source_file": "inventree/contrib/container/gunicorn.conf.py", "source_location": "L3", "weight": 1.0}, {"source": "inventree_contrib_container_gunicorn_conf_py", "target": "multiprocessing", "relation": "imports", "confidence": "EXTRACTED", "source_file": "inventree/contrib/container/gunicorn.conf.py", "source_location": "L4", "weight": 1.0}, {"source": "inventree_contrib_container_gunicorn_conf_py", "target": "os", "relation": "imports", "confidence": "EXTRACTED", "source_file": "inventree/contrib/container/gunicorn.conf.py", "source_location": "L5", "weight": 1.0}, {"source": "inventree_contrib_container_gunicorn_conf_py", "target": "gunicorn_conf_post_fork", "relation": "contains", "confidence": "EXTRACTED", "source_file": "inventree/contrib/container/gunicorn.conf.py", "source_location": "L45", "weight": 1.0}, {"source": "gunicorn_conf_rationale_1", "target": "inventree_contrib_container_gunicorn_conf_py", "relation": "rationale_for", "confidence": "EXTRACTED", "source_file": "inventree/contrib/container/gunicorn.conf.py", "source_location": "L1", "weight": 1.0}, {"source": "gunicorn_conf_rationale_46", "target": "gunicorn_conf_post_fork", "relation": "rationale_for", "confidence": "EXTRACTED", "source_file": "inventree/contrib/container/gunicorn.conf.py", "source_location": "L46", "weight": 1.0}], "raw_calls": [{"caller_nid": "gunicorn_conf_post_fork", "callee": "setup_tracing", "source_file": "inventree/contrib/container/gunicorn.conf.py", "source_location": "L56"}, {"caller_nid": "gunicorn_conf_post_fork", "callee": "setup_instruments", "source_file": "inventree/contrib/container/gunicorn.conf.py", "source_location": "L57"}]}